Metadata-Version: 2.1
Name: rtspwebviewer-ffmpeg
Version: 0.0.1
Summary: Web viewer for RTSP streams that relies on ffmpeg.
Home-page: https://github.com/luiscarlosgph/rtspwebviewer
Author: Luis C. Garcia-Peraza Herrera
Author-email: luiscarlos.gph@gmail.com
License: MIT
Platform: UNKNOWN
License-File: LICENSE
